{
  "id": 577972,
  "title": "\"บีจี\"คว้า\"เฉลิมศักดิ์ อักขี\"เสริมรับ | เดลินิวส์",
  "description": "\u0027บีจี\u0027 ได้ \u0027เฉลิมศักดิ์ อักขี\u0027 จาก \u0027อุบล ยูเอ็มที\u0027 เสริมทัพแล้ว",
  "keywords": "เฉลิมศักดิ์ อักขี, บอลไทย, ทีมชาติ,เดลินิวส์,เดลินิวส์ออนไลน์,เดลินิวส์วันนี้,ข่าวเดลินิวส์ออนไลน์,ข่าวเดลินิวส์ล่าสุด,ข่าว,ข่าวด่วน,ข่าววันนี้,ข่าวร้อน,ข่าวบันเทิง,ข่าวเด่นวันนี้,ข่าวดารา,ข่าวล่าสุด,คลิป,คลิปด่วน,คลิปข่าว,คลิปร้อน,คลิปฮอต,ท่องเที่ยว,สกู๊ปพิเศษ,ไลฟ์สไตล์,lifestyle,ความงาม,เรื่องย่อละคร,เทคนิค,ดวง,ตรวจหวย,special scoop,dailynews,เซ็กซ์,ไอที,ทิป,ยานยนตร์,หนังสือพิมพ์,สาระน่ารู้,ข่าวล่าสุด,สุขภาพ,แต่งบ้าน,อาหาร,แฟชั่น",
  "category": "sports",
  "content": "\"กระต่ายแก้ว\" บางกอกกล๊าส เอฟซี คว้าตัว \"เจ้าเป็ด\" เฉลิมศักดิ์ อักขี กองหลังวัย 22 ปี จาก จากอุบล ยูเอ็มที ยูไนเต็ด โดยเหลือเพียงขั้นตอนการเจรจาในรายละเอียดกับตัวนักเตะ รวมถึงการตรวจร่างกายเท่านั้น โดยเขาเพิ่งถูก มิโลวาน ราเยวัช เรียกติดทีมชาติไทย ชุด 35 คนแรก แต่ไม่มีในโผ 22 คน ที่ไปอุ่นเครื่องกับ อุซเบกิสถาน  ",
  "url": "https://www.dailynews.co.th/sports/577972",
  "date": "2017-06-05T12:06:35.978Z"
}