{
  "id": 578193,
  "title": "ลุ้น4ราศีกิ๊กเก่าขอรีเทิร์นรัก คนที่โหยหากลับมาไม่คาดฝัน | เดลินิวส์",
  "description": "ลุ้น 4 ราศี ที่มีเกณฑ์รีเทิร์นคนคุยเก่า ที่แค่เคยคุย แต่ไม่เคยคบ แต่ครั้งนี้จะได้คบ คนที่เราโหยหาจะกลับมาแบบไม่คาดฝัน",
  "keywords": "ลุ้น4ราศีกิ๊กเก่าขอรีเทิร์นรัก,คนที่โหยหากลับมาไม่คาดฝัน,เดลินิวส์,เดลินิวส์ออนไลน์,เดลินิวส์,เดลินิวส์ออนไลน์,เดลินิวส์วันนี้,ข่าวเดลินิวส์ออนไลน์,ข่าวเดลินิวส์ล่าสุด,ข่าว,ข่าวด่วน,ข่าววันนี้,ข่าวร้อน,ข่าวบันเทิง,ข่าวเด่นวันนี้,ข่าวดารา,ข่าวล่าสุด,คลิป,คลิปด่วน,คลิปข่าว,คลิปร้อน,คลิปฮอต,ท่องเที่ยว,สกู๊ปพิเศษ,ไลฟ์สไตล์,lifestyle,ความงาม,เรื่องย่อละคร,เทคนิค,ดวง,ตรวจหวย,special scoop,dailynews,เซ็กซ์,ไอที,ทิป,ยานยนตร์,หนังสือพิมพ์,สาระน่ารู้,ข่าวล่าสุด,สุขภาพ,แต่งบ้าน,อาหาร,แฟชั่น",
  "category": "entertainment",
  "content": "เมื่อวันที่ 6 มิ.ย. เพจ หมอเค้ก Magic designs หมอดูชื่อดังในโลกออนไลน์ ทำนาย \"กงล้อแห่งการเวลา...โชคชะตาของความรัก รักที่ผ่านมา ไม่มีความสุข รักกับคนที่ไม่ใช่  ชีวิตรักเหมือนเส้นขนาน รักที่ไม่มีความสุข มันกำลังเริ่มหายไป ความรักที่สมหวังกำลังมา คนที่เราโหยหาจะกลับมาแบบไม่คาดฝัน คนที่ไม่มีความสุขในชีวิตคู่ก็มีเกณฑ์ คนรักกลับมาเติมในส่วนที่ขาดหายไป จะกลับมามีชีวิตชีวาอีกครั้ง หัวใจตอนนี้อาจไม่ได้เต้นแรง เหมือนพบรักใหม่ๆ แต่รักครั้งนี้ ที่จะกลับมามันจะเป็นความรักแบบผู้ใหญ่ รักที่เข้าใจ รักที่เติมเต็ม ไม่ใช่รักที่ร้อนแรง แต่เป็นรักที่แข็งแรง มากกว่ารัก ในครั้งนั้นที่เคยผ่านมา ให้ไปทำบุญ ถวายแจกันคู่หรือถวายเทียนคู่ หูตาจะได้สว่างแสงสว่างจะได้นำพา คู่ที่ดี และจุดไฟรัก...อันอบอุ่นอีกครั้ง\" สำหรับ 4 ราศี ที่มีเกณฑ์รีเทิร์นคนคุยเก่า ที่แค่เคยคุย แต่ไม่เคยคบ แต่ครั้งนี้จะได้คบได้แก่ชาวราศีมังกร เมษ สิงห์ และกันย์ โดยตั้งแต่วันที่ 2 มิ.ย.-16 ธ.ค.นี้ ดวงความรักจะกลับตาลปัตร คนเคยคุยจะกลับมามีความรักเกิดขึ้นในหัวใจอีกครั้ง พบรักแบบไม่คาดคิด เขาจะกลับมาพร้อมกับการเต็มเติมสิ่งที่เรา ไม่เคยได้รับจากใคร คือ \"ความสุข\". ขอบคุณเพจ หมอเค้ก Magic designs ",
  "url": "https://www.dailynews.co.th/entertainment/578193",
  "date": "2017-06-06T14:00:57.460Z"
}